{
	"name": "5_pl_copy_all_tbl_files_batch_cnt_4",
	"properties": {
		"activities": [
			{
				"name": "Lookup1",
				"type": "Lookup",
				"dependsOn": [],
				"policy": {
					"timeout": "0.12:00:00",
					"retry": 0,
					"retryIntervalInSeconds": 30,
					"secureOutput": false,
					"secureInput": false
				},
				"userProperties": [],
				"typeProperties": {
					"source": {
						"type": "AzureSqlSource",
						"sqlReaderQuery": {
							"value": "SELECT TABLE_SCHEMA, TABLE_NAME FROM INFORMATION_SCHEMA.TABLES \nWHERE TABLE_SCHEMA='SALESLT' AND TABLE_TYPE='BASE TABLE';",
							"type": "Expression"
						},
						"queryTimeout": "02:00:00",
						"partitionOption": "None"
					},
					"dataset": {
						"referenceName": "ds_azsql_general_use_tbl",
						"type": "DatasetReference",
						"parameters": {
							"schemaName": "SalesLT",
							"tableName": "Customer"
						}
					},
					"firstRowOnly": false
				}
			},
			{
				"name": "ForEach1",
				"type": "ForEach",
				"dependsOn": [
					{
						"activity": "Lookup1",
						"dependencyConditions": [
							"Succeeded"
						]
					}
				],
				"userProperties": [],
				"typeProperties": {
					"items": {
						"value": "@activity('Lookup1').output.value",
						"type": "Expression"
					},
					"isSequential": false,
					"batchCount": 4,
					"activities": [
						{
							"name": "Execute Pipeline tbl_to_files_generic_use",
							"type": "ExecutePipeline",
							"dependsOn": [],
							"userProperties": [],
							"typeProperties": {
								"pipeline": {
									"referenceName": "1_pl_copy_azsql_tbl_to_adls_snappy_parquet_files",
									"type": "PipelineReference"
								},
								"waitOnCompletion": false,
								"parameters": {
									"pl_pram_src_schemaName": {
										"value": "@item().TABLE_SCHEMA",
										"type": "Expression"
									},
									"pl_param_src_tableName": {
										"value": "@item().TABLE_NAME",
										"type": "Expression"
									}
								}
							}
						}
					]
				}
			}
		],
		"annotations": []
	}
}